drb/drivers/java/__init__.py
drb/drivers/java/_version.py
drb/drivers/java/drb_driver_java_call.py
drb/drivers/java/drb_driver_java_factory.py
drb/drivers/java/drb_driver_java_node.py
drb/drivers/java/drbdriver_java_stream.py
drb/drivers/java/libs/__init__.py
drb/drivers/java/libs/antlr-2.7.5.jar
drb/drivers/java/libs/arq-2.1.jar
drb/drivers/java/libs/arq-extra-2.1.jar
drb/drivers/java/libs/bsh-2.0b4.jar
drb/drivers/java/libs/commons-codec-1.4.jar
drb/drivers/java/libs/commons-logging-api-1.1.jar
drb/drivers/java/libs/concurrent-jena-1.3.2.jar
drb/drivers/java/libs/cortex-core-1.0.3.jar
drb/drivers/java/libs/drb-2.6.0.jar
drb/drivers/java/libs/drbx-cortex-1.0.8.jar
drb/drivers/java/libs/drbx-impl-python-1.0.0.jar
drb/drivers/java/libs/ehcache-2.10.1.jar
drb/drivers/java/libs/ehcache-core-2.5.0.jar
drb/drivers/java/libs/icu4j-4.8.2.jar
drb/drivers/java/libs/iri-0.5.jar
drb/drivers/java/libs/jcommander-1.27.jar
drb/drivers/java/libs/jena-2.5.4.jar
drb/drivers/java/libs/jenatest-2.5.4.jar
drb/drivers/java/libs/json-jena-1.0.jar
drb/drivers/java/libs/log4j-1.2.12.jar
drb/drivers/java/libs/log4j-api-2.15.0.jar
drb/drivers/java/libs/log4j-core-2.15.0.jar
drb/drivers/java/libs/lucene-core-2.0.0.jar
drb/drivers/java/libs/org.osgi.core-4.0.0.jar
drb/drivers/java/libs/org.restlet-2.0.5.jar
drb/drivers/java/libs/slf4j-api-1.7.7.jar
drb/drivers/java/libs/stax-api-1.0.jar
drb/drivers/java/libs/streams-1.0.19.jar
drb/drivers/java/libs/testng-6.8.13.jar
drb/drivers/java/libs/wstx-asl-3.0.0.jar
drb/drivers/java/libs/xercesImpl-2.7.1.jar
drb/drivers/java/libs/xmlParserAPIs-2.0.2.jar
drb_driver_java-1.4.0.dist-info/LICENCE.txt
drb_driver_java-1.4.0.dist-info/METADATA
drb_driver_java-1.4.0.dist-info/WHEEL
drb_driver_java-1.4.0.dist-info/entry_points.txt
drb_driver_java-1.4.0.dist-info/top_level.txt
drb_driver_java-1.4.0.dist-info/RECORD
