Metadata-Version: 2.1
Name: drb-driver-java
Version: 1.4.0
Summary: DRB Java Driver
Home-page: https://gitlab.com/drb-python/impl/java
Author: GAEL Systems
Author-email: drb-python@gael.fr
License: LGPLv3
Project-URL: Documentation, https://drb-python.gitlab.io/impl/java
Project-URL: Source, https://gitlab.com/drb-python/impl/java'
Classifier: Programming Language :: Python :: 3.8
Classifier: License :: OSI Approved :: GNU Lesser General Public License v3 (LGPLv3)
Classifier: Operating System :: OS Independent
Requires-Python: >=3.8
License-File: LICENCE.txt
Requires-Dist: cython
Requires-Dist: drb ~=2.2.0
Requires-Dist: pyjnius >=1.4.1
